walytis_beta/__init__.py
walytis_beta/__main__.py
walytis_beta/block_ancestry.py
walytis_beta/block_networking.py
walytis_beta/block_records.py
walytis_beta/exceptions.py
walytis_beta/networking.py
walytis_beta/pip_install.py
walytis_beta/walytis_beta.py
walytis_beta/walytis_beta_api_terminal.py
walytis_beta/walytis_beta_appdata.py
walytis_beta-2.4.34.dist-info/licenses/LICENSE
walytis_beta-2.4.34.dist-info/licenses/LICENSE-CC0
walytis_beta_api/__init__.py
walytis_beta_api/__main__.py
walytis_beta_api/block_model.py
walytis_beta_api/blockchain_model.py
walytis_beta_api/exceptions.py
walytis_beta_api/versions.py
walytis_beta_api/walytis_beta_brenthy_api.py
walytis_beta_api/walytis_beta_embedded_api.py
walytis_beta_api/walytis_beta_generic_interface.py
walytis_beta_api/walytis_beta_interface.py
walytis_beta_api/_experimental/__init__.py
walytis_beta_api/_experimental/generic_blockchain.py
walytis_beta_api/_experimental/generic_blockchain_testing.py
walytis_beta_tools/__init__.py
walytis_beta_tools/block_model.py
walytis_beta_tools/exceptions.py
walytis_beta_tools/log.py
walytis_beta_tools/versions.py
walytis_beta_tools/_experimental/__init__.py
walytis_beta_tools/_experimental/block_lazy_loading.py
walytis_beta_tools/_experimental/config.py
walytis_beta_tools/_experimental/generic_block.py
walytis_beta_tools/_experimental/ipfs_interface.py
walytis_beta-2.4.34.dist-info/METADATA
walytis_beta-2.4.34.dist-info/WHEEL
walytis_beta-2.4.34.dist-info/top_level.txt
walytis_beta-2.4.34.dist-info/RECORD
