Metadata-Version: 2.4
Name: walytis_beta
Version: 2.4.34
Summary: A flexible, lightweight, nonlinear database-blockchain. Built to be built upon.
Author: Emendir
Project-URL: Homepage, https://github.com/emendir/Walytis_Beta
Project-URL: Documentation, https://github.com/emendir/Walytis_Beta/blob/master/docs/DocsOverview.md
Project-URL: Repository, https://github.com/emendir/Walytis_Beta.git
Project-URL: IPFS, https://ipfs.io/ipns/k2k4r8nismm5mmgrox2fci816xvj4l4cudnuc55gkfoealjuiaexbsup/Projects/Walytis
Requires-Python: >=3.11
License-File: LICENSE
License-File: LICENSE-CC0
Requires-Dist: termcolor
Requires-Dist: tqdm
Requires-Dist: eciespy
Requires-Dist: ipfs_tk>=0.1.11
Requires-Dist: ipfs_toolkit>=0.6.0rc8
Requires-Dist: ipfs_node>=0.1.12rc5
Requires-Dist: brenthy_tools_beta>=4.0.11
Requires-Dist: emtest>=0.0.7
Requires-Dist: appdirs>=1.4.3
Requires-Dist: pyzmq>=25.1.1
Dynamic: license-file
